sv_alu/alu.sv
module alu (
    input logic [31:0] a, // Operadnd a
    input logic [31:0] b, // Operand b
    input logic [3:0] op, // Operation code
    output logic [31:0] result, // Result of the operation
    output logic zero, // Zero flag
    output logic negative, // Negative flag
    output logic overflow, // Overflow flag
    output logic carry // Carry flag
);

    logic [4:0]  shamt;
    logic [32:0] carry_result;

    assign shamt = b[4:0];
    assign carry_result = {1'b0, a} + {1'b0, b};

    always_comb begin
        case (op)
            4'b0000: result = a + b; // ADD
            4'b0001: result = a - b; // SUB
            4'b0010: result = a & b; // AND
            4'b0011: result = a | b; // OR
            4'b0100: result = ~(a | b); // NOR
            4'b0101: result = a ^ b; // XOR
            4'b0110: result = a << shamt; // SLL
            4'b0111: result = a >> shamt; // SRL
            4'b1000: result = $signed(a) >>> shamt; // SRA
            4'b1001: result = ($signed(a) < $signed(b)) ? 32'd1 : 32'd0; // SLT
            4'b1010: result = ($unsigned(a) < $unsigned(b)) ? 32'd1 : 32'd0; // SLTU
            4'b1011: result = a + {b[31:12], 12'b0}; // AUIPC — add upper immediate to PC
            4'b1100: result = {b[31:12], 12'b0}; // LUI
            4'b1101: result = a; // PASSA
            4'b1110: result = b; // PASSB
            4'b1111: result = 32'd0; // ZERO
            default: result = 32'd0; // Default case
        endcase 
    end

    assign zero = (result == 32'd0); // Set zero flag
    assign negative = result[31]; // Set negative flag
    assign overflow = ~(a[31] ^ b[31]) & (a[31] ^ result[31]); // Set overflow flag for addition
    assign carry = carry_result[32]; // Set carry flag
    
endmodule

sv_alu/alu_tb.sv
module alu_tb;
    // Terminal Run:
    // iverilog -g2012 -o alu_sim alu.sv alu_tb.sv
    // vvp alu_sim
    // gtkwave alu.vcd

    // Testbench signals
    logic [31:0] a;
    logic [31:0] b;
    logic [3:0] op;
    logic [31:0] result;
    logic zero;

    // Instantiate the ALU
    logic negative;
    logic overflow;
    logic carry;

    alu dut (
        .a(a),
        .b(b),
        .op(op),
        .result(result),
        .zero(zero),
        .negative(negative),
        .overflow(overflow),
        .carry(carry)
    );

    // Test procedure
    initial begin
        $display("Starting ALU Testbench");
        $dumpfile("alu.vcd");   // for gtkwave
        $dumpvars(0, alu_tb);

        /////////////////////////////////////////////
        // test ADD
        a = 32'd10; b = 32'd5; op = 4'b0000;
        #10;
        $display("ADD: %0d + %0d = %0d (expect 15)", a, b, result);

        $display("");
        /////////////////////////////////////////////
        // test SUB
        a = 32'd10; b = 32'd10; op = 4'b0001;
        #10;
        $display("SUB: %0d - %0d = %0d  zero=%b (expect 0, zero=1)", a, b, result, zero);

        $display("");
        /////////////////////////////////////////////
        // test AND
        a = 32'hFF; b = 32'h0F; op = 4'b0010;
        #10;
        $display("AND: %h & %h = %h (expect 0f)", a, b, result);

        $display("");
        /////////////////////////////////////////////
        // test OR
        a = 32'hF0; b = 32'h0F; op = 4'b0011;
        #10;
        $display("OR: %h | %h = %h (expect ff)", a, b, result);

        $display("");
        /////////////////////////////////////////////
        // test NOR
        a = 32'hF0; b = 32'h0F; op = 4'b0100;
        #10;
        $display("NOR: %h ~| %h = %h (expect 00)", a, b, result);

        $display("");
        ///////////////////////////////////////////////
        // test XOR
        a = 32'hF0; b = 32'h00; op = 4'b0101;
        #10;
        $display("XOR: %h ^ %h = %h (expect f0)", a, b, result);

        $display("");
        /////////////////////////////////////////////
        // test SLL
        a = 32'd1; b = 32'd4; op = 4'b0110;
        #10;
        $display("SLL: %b << %0d = %b (expect 00000000000000000000000000010000)", a, b[4:0], result);

        // SLL by 0 — result should equal a unchanged
        a = 32'd15; b = 32'd0; op = 4'b0110;
        #10;
        $display("SLL by 0: %b (expect 00000000000000000000000000001111)", result);

        // SLL by 31 — shift all the way to the sign bit
        a = 32'd1; b = 32'd31; op = 4'b0110;
        #10;
        $display("SLL by 31: %b (expect 10000000000000000000000000000000)", result);

        $display("");
        /////////////////////////////////////////////
        // test SRL
        a = 32'h80000000; b = 32'd1; op = 4'b0111;
        #10;
        $display("SRL: %b >> %0d = %b (expect 01000000000000000000000000000000)", a, b[4:0], result);

        // SRL by 0 — result should equal a unchanged
        a = 32'hF0F0F0F0; b = 32'd0; op = 4'b0111;
        #10;
        $display("SRL by 0: %b (expect 11110000111100001111000011110000)", result);

        // SRL by 4
        a = 32'hF0; b = 32'd4; op = 4'b0111;
        #10;
        $display("SRL by 4: %b (expect 00000000000000000000000000001111)", result);

        // SRL by 31 — only top bit survives
        a = 32'h80000000; b = 32'd31; op = 4'b0111;
        #10;
        $display("SRL by 31: %b (expect 00000000000000000000000000000001)", result);

        $display("");
        /////////////////////////////////////////////
        // test SRA
        a = 32'h80000000; b = 32'd1; op = 4'b1000;
        #10;
        $display("SRA neg: %b >> %0d = %b (expect 11000000000000000000000000000000)", a, b[4:0], result);

        // SRA — positive number, behaves same as SRL
        a = 32'h40000000; b = 32'd1; op = 4'b1000;
        #10;
        $display("SRA pos: %b >> %0d = %b (expect 00100000000000000000000000000000)", a, b[4:0], result);

        // SRA by 4 — negative number, top 4 bits should all become 1
        a = 32'hF0000000; b = 32'd4; op = 4'b1000;
        #10;
        $display("SRA by 4: %b (expect 11111111000000000000000000000000)", result);

        // SRA by 31 — all bits become copies of sign bit
        a = 32'h80000000; b = 32'd31; op = 4'b1000;
        #10;
        $display("SRA by 31: %b (expect 11111111111111111111111111111111)", result);

        // SRA by 31 — positive number all bits become 0
        a = 32'h40000000; b = 32'd31; op = 4'b1000;
        #10;
        $display("SRA by 31 pos: %b (expect 00000000000000000000000000000000)", result);

        $display("");
        /////////////////////////////////////////////
        // SLT basic — a clearly less than b
        a = 32'd5; b = 32'd10; op = 4'b1001;
        #10;
        $display("SLT 5<10: %0d (expect 1)", result);

        // SLT basic — a greater than b
        a = 32'd10; b = 32'd5; op = 4'b1001;
        #10;
        $display("SLT 10<5: %0d (expect 0)", result);

        // SLT equal — should output 0
        a = 32'd7; b = 32'd7; op = 4'b1001;
        #10;
        $display("SLT 7<7: %0d (expect 0)", result);

        // SLT negative vs positive — critical signed test
        a = 32'hFFFFFFFF; b = 32'd1; op = 4'b1001;
        #10;
        $display("SLT -1<1: %0d (expect 1)", result);

        // SLT positive vs negative — should be 0
        a = 32'd1; b = 32'hFFFFFFFF; op = 4'b1001;
        #10;
        $display("SLT 1<-1: %0d (expect 0)", result);

        // SLT most negative vs most positive
        a = 32'h80000000; b = 32'h7FFFFFFF; op = 4'b1001;
        #10;
        $display("SLT MIN<MAX: %0d (expect 1)", result);

        // SLT most positive vs most negative
        a = 32'h7FFFFFFF; b = 32'h80000000; op = 4'b1001;
        #10;
        $display("SLT MAX<MIN: %0d (expect 0)", result);


        $display("");
        /////////////////////////////////////////////
        // SLTU basic — a clearly less than b
        a = 32'd5; b = 32'd10; op = 4'b1010;
        #10;
        $display("SLTU 5<10: %0d (expect 1)", result);

        // SLTU basic — a greater than b
        a = 32'd10; b = 32'd5; op = 4'b1010;
        #10;
        $display("SLTU 10<5: %0d (expect 0)", result);

        // SLTU equal — should output 0
        a = 32'd7; b = 32'd7; op = 4'b1010;
        #10;
        $display("SLTU 7<7: %0d (expect 0)", result);

        // SLTU critical — same bits as SLT -1<1 test but now unsigned
        // 0xFFFFFFFF unsigned = 4294967295, NOT less than 1
        a = 32'hFFFFFFFF; b = 32'd1; op = 4'b1010;
        #10;
        $display("SLTU 0xFFFFFFFF<1: %0d (expect 0)", result);

        // SLTU — 1 vs 0xFFFFFFFF, 1 IS less than 4294967295 unsigned
        a = 32'd1; b = 32'hFFFFFFFF; op = 4'b1010;
        #10;
        $display("SLTU 1<0xFFFFFFFF: %0d (expect 1)", result);

        // SLTU — 0x80000000 unsigned is a large number, NOT less than 0x7FFFFFFF
        a = 32'h80000000; b = 32'h7FFFFFFF; op = 4'b1010;
        #10;
        $display("SLTU 0x80000000<0x7FFFFFFF: %0d (expect 0)", result);

        // SLTU — 0x7FFFFFFF IS less than 0x80000000 unsigned
        a = 32'h7FFFFFFF; b = 32'h80000000; op = 4'b1010;
        #10;
        $display("SLTU 0x7FFFFFFF<0x80000000: %0d (expect 1)", result);


        $display("");
        //////////////////////////////////////////////////////////////////////
        // AUIPC basic — ALU masks bottom 12 bits of b internally
        a = 32'h00001000; b = 32'h00005FFF; op = 4'b1011;
        #10;
        $display("AUIPC: %h + upper(%h) = %h (expect 00006000)", a, b, result);

        // AUIPC — PC at zero
        a = 32'h00000000; b = 32'h00005FFF; op = 4'b1011;
        #10;
        $display("AUIPC PC=0: %h (expect 00005000)", result);

        // AUIPC — bottom 12 bits of b should be ignored
        a = 32'h00000000; b = 32'h00001FFF; op = 4'b1011;
        #10;
        $display("AUIPC mask test: %h (expect 00001000)", result);

        // AUIPC — PC at realistic mid-program address
        a = 32'h00000400; b = 32'h000FF000; op = 4'b1011;
        #10;
        $display("AUIPC mid: %h (expect 000FF400)", result);

        // AUIPC — upper immediate zero, result should equal PC
        a = 32'h00001000; b = 32'h00000FFF; op = 4'b1011;
        #10;
        $display("AUIPC imm=0: %h (expect 00001000)", result);

        $display("");
        ////////////////////////////////////////////////////////////////////////
        // test LUI
        a = 32'h00000000; b = 32'hABCDE000; op = 4'b1100;
        #10;
        $display("LUI: %h (expect ABCDE000)", result);

        a = 32'h00000000; b = 32'hABCDEFFF; op = 4'b1100;
        #10;
        $display("LUI mask: %h (expect ABCDE000)", result);

        a = 32'h00000000; b = 32'h00000FFF; op = 4'b1100;
        #10;
        $display("LUI zero upper: %h (expect 00000000)", result);

        $display("");
        ////////////////////////////////////////////////////////////////////////
        // test PASSA
        a = 32'hDEADBEEF; b = 32'h00000000; op = 4'b1101;
        #10;
        $display("PASSA: %h (expect DEADBEEF)", result);

        a = 32'h00000000; b = 32'hDEADBEEF; op = 4'b1101;
        #10;
        $display("PASSA ignores b: %h (expect 00000000)", result);


        $display("");
        ////////////////////////////////////////////////////////////////////////
        // test PASSB
        a = 32'h00000000; b = 32'hCAFEBABE; op = 4'b1110;
        #10;
        $display("PASSB: %h (expect CAFEBABE)", result);

        a = 32'hDEADBEEF; b = 32'h00000000; op = 4'b1110;
        #10;
        $display("PASSB ignores a: %h (expect 00000000)", result);

        $display("");
        ////////////////////////////////////////////////////////////////////////
        // test ZERO
        a = 32'hDEADBEEF; b = 32'hCAFEBABE; op = 4'b1111;
        #10;
        $display("ZERO: %h (expect 00000000)", result);
        assert(result == 32'd0) else $fatal(1, "ZERO failed!");
        assert(zero == 1'b1)    else $fatal(1, "ZERO zero flag failed!");

        $display("");
        ////////////////////////////////////////////////////////////////////////
        // test DEFAULT
        a = 32'hDEADBEEF; b = 32'hCAFEBABE; op = 4'bXXXX;
        #10;
        $display("DEFAULT: %h (expect 00000000)", result);

        $finish;
    end
endmodule

sv_alu/alu.vcd
$date
	Fri Jun  5 16:54:26 2026
$end
$version
	Icarus Verilog
$end
$timescale
	1s
$end
$scope module alu_tb $end
$var wire 1 ! zero $end
$var wire 32 " result [31:0] $end
$var wire 1 # overflow $end
$var wire 1 $ negative $end
$var wire 1 % carry $end
$var reg 32 & a [31:0] $end
$var reg 32 ' b [31:0] $end
$var reg 4 ( op [3:0] $end
$scope module dut $end
$var wire 32 ) a [31:0] $end
$var wire 32 * b [31:0] $end
$var wire 4 + op [3:0] $end
$var wire 1 # overflow $end
$var wire 1 ! zero $end
$var wire 5 , shamt [4:0] $end
$var wire 1 $ negative $end
$var wire 33 - carry_result [32:0] $end
$var wire 1 % carry $end
$var reg 32 . result [31:0] $end
$upscope $end
$upscope $end
$enddefinitions $end
$comment Show the parameter values. $end
$dumpall
$end
#0
$dumpvars
b1111 .
b1111 -
b101 ,
b0 +
b101 *
b1010 )
b0 (
b101 '
b1010 &
0%
0$
0#
b1111 "
0!
$end
#10
1!
b0 "
b0 .
b1010 ,
b1 (
b1 +
b10100 -
b1010 '
b1010 *
#20
b1111 ,
0!
b1111 "
b1111 .
b10 (
b10 +
b1111 '
b1111 *
b100001110 -
b11111111 &
b11111111 )
#30
b11111111 "
b11111111 .
b11 (
b11 +
b11111111 -
b11110000 &
b11110000 )
#40
1#
1$
b11111111111111111111111100000000 "
b11111111111111111111111100000000 .
b100 (
b100 +
#50
0#
0$
b11110000 "
b11110000 .
b0 ,
b101 (
b101 +
b11110000 -
b0 '
b0 *
#60
b100 ,
b10000 "
b10000 .
b110 (
b110 +
b100 '
b100 *
b101 -
b1 &
b1 )
#70
b0 ,
b1111 "
b1111 .
b0 '
b0 *
b1111 -
b1111 &
b1111 )
#80
1#
1$
b11111 ,
b10000000000000000000000000000000 "
b10000000000000000000000000000000 .
b11111 '
b11111 *
b100000 -
b1 &
b1 )
#90
0#
0$
b1 ,
b1000000000000000000000000000000 "
b1000000000000000000000000000000 .
b111 (
b111 +
b1 '
b1 *
b10000000000000000000000000000001 -
b10000000000000000000000000000000 &
b10000000000000000000000000000000 )
#100
1$
b0 ,
b11110000111100001111000011110000 "
b11110000111100001111000011110000 .
b0 '
b0 *
b11110000111100001111000011110000 -
b11110000111100001111000011110000 &
b11110000111100001111000011110000 )
#110
0$
b100 ,
b1111 "
b1111 .
b100 '
b100 *
b11110100 -
b11110000 &
b11110000 )
#120
0#
b11111 ,
b1 "
b1 .
b11111 '
b11111 *
b10000000000000000000000000011111 -
b10000000000000000000000000000000 &
b10000000000000000000000000000000 )
#130
1$
b11000000000000000000000000000000 "
b11000000000000000000000000000000 .
b1 ,
b1000 (
b1000 +
b10000000000000000000000000000001 -
b1 '
b1 *
#140
0$
b100000000000000000000000000000 "
b100000000000000000000000000000 .
b1000000000000000000000000000001 -
b1000000000000000000000000000000 &
b1000000000000000000000000000000 )
#150
0#
1$
b100 ,
b11111111000000000000000000000000 "
b11111111000000000000000000000000 .
b100 '
b100 *
b11110000000000000000000000000100 -
b11110000000000000000000000000000 &
b11110000000000000000000000000000 )
#160
b11111 ,
b11111111111111111111111111111111 "
b11111111111111111111111111111111 .
b11111 '
b11111 *
b10000000000000000000000000011111 -
b10000000000000000000000000000000 &
b10000000000000000000000000000000 )
#170
0$
1!
b0 "
b0 .
b1000000000000000000000000011111 -
b1000000000000000000000000000000 &
b1000000000000000000000000000000 )
#180
b1010 ,
0!
b1 "
b1 .
b1001 (
b1001 +
b1010 '
b1010 *
b1111 -
b101 &
b101 )
#190
b101 ,
1!
b0 "
b0 .
b101 '
b101 *
b1111 -
b1010 &
b1010 )
#200
b111 ,
b111 '
b111 *
b1110 -
b111 &
b111 )
#210
0#
b1 ,
0!
b1 "
b1 .
1%
b1 '
b1 *
b100000000000000000000000000000000 -
b11111111111111111111111111111111 &
b11111111111111111111111111111111 )
#220
b11111 ,
1!
b0 "
b0 .
b11111111111111111111111111111111 '
b11111111111111111111111111111111 *
b100000000000000000000000000000000 -
b1 &
b1 )
#230
0%
0!
b1 "
b1 .
b1111111111111111111111111111111 '
b1111111111111111111111111111111 *
b11111111111111111111111111111111 -
b10000000000000000000000000000000 &
b10000000000000000000000000000000 )
#240
b0 ,
1!
b0 "
b0 .
b10000000000000000000000000000000 '
b10000000000000000000000000000000 *
b11111111111111111111111111111111 -
b1111111111111111111111111111111 &
b1111111111111111111111111111111 )
#250
b1010 ,
0!
b1 "
b1 .
b1010 (
b1010 +
b1010 '
b1010 *
b1111 -
b101 &
b101 )
#260
b101 ,
1!
b0 "
b0 .
b101 '
b101 *
b1111 -
b1010 &
b1010 )
#270
b111 ,
b111 '
b111 *
b1110 -
b111 &
b111 )
#280
0#
b1 ,
1%
b1 '
b1 *
b100000000000000000000000000000000 -
b11111111111111111111111111111111 &
b11111111111111111111111111111111 )
#290
b11111 ,
0!
b1 "
b1 .
b11111111111111111111111111111111 '
b11111111111111111111111111111111 *
b100000000000000000000000000000000 -
b1 &
b1 )
#300
0%
1!
b0 "
b0 .
b1111111111111111111111111111111 '
b1111111111111111111111111111111 *
b11111111111111111111111111111111 -
b10000000000000000000000000000000 &
b10000000000000000000000000000000 )
#310
b0 ,
0!
b1 "
b1 .
b10000000000000000000000000000000 '
b10000000000000000000000000000000 *
b11111111111111111111111111111111 -
b1111111111111111111111111111111 &
b1111111111111111111111111111111 )
#320
b11111 ,
b110000000000000 "
b110000000000000 .
b1011 (
b1011 +
b101111111111111 '
b101111111111111 *
b110111111111111 -
b1000000000000 &
b1000000000000 )
#330
b101000000000000 "
b101000000000000 .
b101111111111111 -
b0 &
b0 )
#340
b1000000000000 "
b1000000000000 .
b1111111111111 -
b1111111111111 '
b1111111111111 *
#350
b0 ,
b11111111010000000000 "
b11111111010000000000 .
b11111111000000000000 '
b11111111000000000000 *
b11111111010000000000 -
b10000000000 &
b10000000000 )
#360
b11111 ,
b1000000000000 "
b1000000000000 .
b111111111111 '
b111111111111 *
b1111111111111 -
b1000000000000 &
b1000000000000 )
#370
1$
b0 ,
b10101011110011011110000000000000 "
b10101011110011011110000000000000 .
b1100 (
b1100 +
b10101011110011011110000000000000 '
b10101011110011011110000000000000 *
b10101011110011011110000000000000 -
b0 &
b0 )
#380
b11111 ,
b10101011110011011110111111111111 -
b10101011110011011110111111111111 '
b10101011110011011110111111111111 *
#390
0$
1!
b0 "
b0 .
b111111111111 -
b111111111111 '
b111111111111 *
#400
0#
1$
b0 ,
0!
b11011110101011011011111011101111 "
b11011110101011011011111011101111 .
b1101 (
b1101 +
b0 '
b0 *
b11011110101011011011111011101111 -
b11011110101011011011111011101111 &
b11011110101011011011111011101111 )
#410
0$
b1111 ,
1!
b0 "
b0 .
b11011110101011011011111011101111 '
b11011110101011011011111011101111 *
b11011110101011011011111011101111 -
b0 &
b0 )
#420
1$
0!
b11001010111111101011101010111110 "
b11001010111111101011101010111110 .
b11110 ,
b1110 (
b1110 +
b11001010111111101011101010111110 -
b11001010111111101011101010111110 '
b11001010111111101011101010111110 *
#430
0$
b0 ,
1!
b0 "
b0 .
b0 '
b0 *
b11011110101011011011111011101111 -
b11011110101011011011111011101111 &
b11011110101011011011111011101111 )
#440
1#
b11110 ,
1%
b1111 (
b1111 +
b110101001101011000111100110101101 -
b11001010111111101011101010111110 '
b11001010111111101011101010111110 *
#450
bx (
bx +
