sv_dMem/dMem.sv
module dMem #(
    parameter int DEPTH = 4096 // number of 32-bit words (16 KB)
) (
    input  logic clk,
    input  logic mem_write, // asserted for SB/SH/SW in MEM stage
    input  logic [31:0] addr, // byte address (ALU result: rs1 + imm)
    input  logic [31:0] write_data, // store data (rs2 value)
    input  logic [2:0] funct3, // access width/sign control
    output logic [31:0] read_data // load result (sign/zero-extended)
);

    localparam int WORD_BITS = $clog2(DEPTH);
 
    logic [31:0] mem [0:DEPTH-1];

    // Address decompostion 
    logic [WORD_BITS-1:0] word_addr; //which 32-bit word to access
    logic [1:0] byte_offset; //where inside that word the access starts
 
    assign word_addr   = addr[WORD_BITS+1:2];
    assign byte_offset = addr[1:0];

    // Simulation-only zero initalization
    initial begin
        for (int i = 0; i < DEPTH; i++) mem[i] = 32'h0;
    end


    // Store path
    logic [3:0]  byte_enable;
    logic [31:0] shifted_wdata;
 
    always_comb begin
        shifted_wdata = write_data << (byte_offset * 8);
        case (funct3[1:0])
            2'b00:   byte_enable = 4'b0001 << byte_offset;  // SB
            2'b01:   byte_enable = 4'b0011 << byte_offset;  // SH
            2'b10:   byte_enable = 4'b1111;                 // SW
            default: byte_enable = 4'b0000;
        endcase
    end
 
    always_ff @(posedge clk) begin
        if (mem_write) begin
            if (byte_enable[0]) mem[word_addr][7:0]   <= shifted_wdata[7:0];
            if (byte_enable[1]) mem[word_addr][15:8]  <= shifted_wdata[15:8];
            if (byte_enable[2]) mem[word_addr][23:16] <= shifted_wdata[23:16];
            if (byte_enable[3]) mem[word_addr][31:24] <= shifted_wdata[31:24];
        end
    end

    // Load path
    logic [31:0] raw_word;
    logic [31:0] shifted_rdata;
 
    assign raw_word = mem[word_addr];
    assign shifted_rdata = raw_word >> (byte_offset * 8);
 
    always_comb begin
        case (funct3)
            3'b000:  read_data = {{24{shifted_rdata[7]}},  shifted_rdata[7:0]};  // LB
            3'b001:  read_data = {{16{shifted_rdata[15]}}, shifted_rdata[15:0]}; // LH
            3'b010:  read_data = raw_word;                                       // LW
            3'b100:  read_data = {24'b0, shifted_rdata[7:0]};                    // LBU
            3'b101:  read_data = {16'b0, shifted_rdata[15:0]};                   // LHU
            default: read_data = 32'b0;
        endcase
    end
 
endmodule

sv_dMem/dMem_tb.sv
`timescale 1ns/1ps
 
module dMem_tb;
 
    localparam int DEPTH      = 16;
    localparam int CLK_PERIOD = 10;
 
    logic        clk;
    logic        mem_write;
    logic [31:0] addr;
    logic [31:0] write_data;
    logic [2:0]  funct3;
    logic [31:0] read_data;

    int pass_count = 0;
    int fail_count = 0;
 
    logic [31:0] rand_addr;
    logic [31:0] rand_data;
 
    dMem #(.DEPTH(DEPTH)) dut (
        .clk        (clk),
        .mem_write  (mem_write),
        .addr       (addr),
        .write_data (write_data),
        .funct3     (funct3),
        .read_data  (read_data)
    );

    //Clock setup
    initial clk = 0;
    always #(CLK_PERIOD/2) clk = ~clk;
 
    // funct3 encodings, named for readability in the test sequence
    localparam logic [2:0] F3_B  = 3'b000;  // SB / LB
    localparam logic [2:0] F3_H  = 3'b001;  // SH / LH
    localparam logic [2:0] F3_W  = 3'b010;  // SW / LW
    localparam logic [2:0] F3_BU = 3'b100;  // LBU
    localparam logic [2:0] F3_HU = 3'b101;  // LHU

    // Checker function
    task automatic check(string name, logic [31:0] got, logic [31:0] exp);
        if (got === exp) begin
            pass_count++;
            $display("  PASS %-32s got=%08h", name, got);
        end else begin
            fail_count++;
            $display("  FAIL %-32s got=%08h exp=%08h", name, got, exp);
        end
    endtask

    // Store function
    task automatic do_store(input logic [31:0] a, input logic [31:0] d, input logic [2:0] f3);
        addr = a; write_data = d; funct3 = f3; mem_write = 1;
        @(posedge clk);
        #1;
        mem_write = 0;
    endtask

    // Load function
    task automatic do_load(input logic [31:0] a, input logic [2:0] f3);
        addr = a; funct3 = f3;
        #1;
    endtask

    initial begin
        $dumpfile("dMem_tb.vcd");
        $dumpvars(0, dMem_tb);
 
        mem_write = 0; addr = 0; write_data = 0; funct3 = 0;
        @(posedge clk); #1;

        //-----------------------------------------------------------
        $display("\nTest 1: Word store/load across the address range");
        do_store(32'h0000_0000, 32'hDEAD_BEEF, F3_W);
        do_load(32'h0000_0000, F3_W);
        check("SW/LW word 0", read_data, 32'hDEAD_BEEF);
 
        do_store(32'h0000_0004, 32'h1234_5678, F3_W);
        do_load(32'h0000_0004, F3_W);
        check("SW/LW word 1", read_data, 32'h1234_5678);
 
        do_store((DEPTH-1)*4, 32'hCAFE_F00D, F3_W);   // highest word for this DEPTH
        do_load((DEPTH-1)*4, F3_W);
        check("SW/LW last word (boundary)", read_data, 32'hCAFE_F00D);
 
        do_load(32'h0000_0000, F3_W);
        check("word 0 unaffected by other writes", read_data, 32'hDEAD_BEEF);


        //-----------------------------------------------------------
        $display("\nTest 2: Byte store at all four offsets");
        do_store(32'h0000_0008, 32'h0000_0000, F3_W);  // clear the word first
 
        do_store(32'h0000_0008, 32'h0000_00AA, F3_B);  // offset 0
        do_load(32'h0000_0008, F3_W);
        check("SB offset0 isolated", read_data, 32'h0000_00AA);
 
        do_store(32'h0000_0009, 32'h0000_00BB, F3_B);  // offset 1
        do_load(32'h0000_0008, F3_W);
        check("SB offset1 preserves offset0", read_data, 32'h0000_BBAA);
 
        do_store(32'h0000_000A, 32'h0000_00CC, F3_B);  // offset 2
        do_load(32'h0000_0008, F3_W);
        check("SB offset2 preserves 0,1", read_data, 32'h00CC_BBAA);
 
        do_store(32'h0000_000B, 32'h0000_00DD, F3_B);  // offset 3
        do_load(32'h0000_0008, F3_W);
        check("SB offset3 completes word", read_data, 32'hDDCC_BBAA);
 

        //-----------------------------------------------------------
        $display("\nTest 3: Halfword store at both aligned offsets");
        do_store(32'h0000_000C, 32'h0000_0000, F3_W);  // clear the word
 
        do_store(32'h0000_000C, 32'h0000_1234, F3_H);  // offset 0
        do_load(32'h0000_000C, F3_W);
        check("SH offset0 isolated", read_data, 32'h0000_1234);
 
        do_store(32'h0000_000E, 32'h0000_5678, F3_H);  // offset 2
        do_load(32'h0000_000C, F3_W);
        check("SH offset2 preserves offset0 half", read_data, 32'h5678_1234);
 

        //-----------------------------------------------------------
        $display("\nTest 4: Sign vs. zero extension: byte loads");
        do_store(32'h0000_0000, 32'h0000_007F, F3_B);  // positive byte
        do_load(32'h0000_0000, F3_B);
        check("LB positive, no sign-fill", read_data, 32'h0000_007F);
        do_load(32'h0000_0000, F3_BU);
        check("LBU positive, zero-fill", read_data, 32'h0000_007F);
 
        do_store(32'h0000_0000, 32'h0000_0080, F3_B);  // negative byte
        do_load(32'h0000_0000, F3_B);
        check("LB negative, sign-fill", read_data, 32'hFFFF_FF80);
        do_load(32'h0000_0000, F3_BU);
        check("LBU negative, zero-fill", read_data, 32'h0000_0080);
 

        //-----------------------------------------------------------
        $display("\nTest 5: Sign vs. zero extension: halfword loads");
        do_store(32'h0000_0000, 32'h0000_7FFF, F3_H);  // positive half
        do_load(32'h0000_0000, F3_H);
        check("LH positive, no sign-fill", read_data, 32'h0000_7FFF);
        do_load(32'h0000_0000, F3_HU);
        check("LHU positive, zero-fill", read_data, 32'h0000_7FFF);
 
        do_store(32'h0000_0000, 32'h0000_8055, F3_H);  // negative half
        do_load(32'h0000_0000, F3_H);
        check("LH negative, sign-fill", read_data, 32'hFFFF_8055);
        do_load(32'h0000_0000, F3_HU);
        check("LHU negative, zero-fill", read_data, 32'h0000_8055);
 

        //-----------------------------------------------------------
        $display("\nTest 6: Byte loads at every offset within a mixed-sign word");
        // byte3=0x81(neg) byte2=0x02(pos) byte1=0x03(pos) byte0=0x84(neg)
        do_store(32'h0000_0010, 32'h8102_0384, F3_W);
 
        do_load(32'h0000_0010, F3_B);
        check("LB word byte0 (neg)", read_data, 32'hFFFF_FF84);
        do_load(32'h0000_0011, F3_B);
        check("LB word byte1 (pos)", read_data, 32'h0000_0003);
        do_load(32'h0000_0012, F3_B);
        check("LB word byte2 (pos)", read_data, 32'h0000_0002);
        do_load(32'h0000_0013, F3_B);
        check("LB word byte3 (neg)", read_data, 32'hFFFF_FF81);
 
        do_load(32'h0000_0010, F3_BU);
        check("LBU word byte0", read_data, 32'h0000_0084);
        do_load(32'h0000_0013, F3_BU);
        check("LBU word byte3", read_data, 32'h0000_0081);
 

        //-----------------------------------------------------------
        $display("\nTest 7: mem_write gating: no write when deasserted");
        do_store(32'h0000_0018, 32'hAAAA_AAAA, F3_W);  // seed a known value
 
        addr = 32'h0000_0018; write_data = 32'h5555_5555; funct3 = F3_W; mem_write = 0;
        @(posedge clk); #1;
        do_load(32'h0000_0018, F3_W);
        check("no write when mem_write=0", read_data, 32'hAAAA_AAAA);
 

        //-----------------------------------------------------------
        $display("\nTest 8: Overwrite: last store wins");
        do_store(32'h0000_001C, 32'h1111_1111, F3_W);
        do_store(32'h0000_001C, 32'h2222_2222, F3_W);
        do_load(32'h0000_001C, F3_W);
        check("overwrite keeps latest value", read_data, 32'h2222_2222);
 

        //-----------------------------------------------------------
        $display("\nTest 9: Undefined funct3 encodings");
        do_store(32'h0000_0020, 32'h0000_0000, F3_W);   // clear
        do_store(32'h0000_0020, 32'hFFFF_FFFF, 3'b011); // undefined store width
        do_load(32'h0000_0020, F3_W);
        check("undefined store funct3 writes nothing", read_data, 32'h0000_0000);
 
        do_store(32'h0000_0024, 32'hFFFF_FFFF, F3_W);
        do_load(32'h0000_0024, 3'b110);
        check("undefined load funct3 (110) returns 0", read_data, 32'h0000_0000);
        do_load(32'h0000_0024, 3'b111);
        check("undefined load funct3 (111) returns 0", read_data, 32'h0000_0000);
 

        //-----------------------------------------------------------
        $display("\nTest 10: Uninitialized location reads zero");
        do_load(32'h0000_0028, F3_W);  // word 10 - never written anywhere above
        check("untouched word reads 0", read_data, 32'h0000_0000);
 

        //-----------------------------------------------------------
        $display("\nTest 11: Randomized word store/load regression");
        for (int i = 0; i < 20; i++) begin
            rand_addr = $urandom_range(0, DEPTH-1) * 4;
            rand_data = $urandom;
            do_store(rand_addr, rand_data, F3_W);
            do_load(rand_addr, F3_W);
            check($sformatf("random SW/LW addr=%0d", rand_addr), read_data, rand_data);
        end


        //-----------------------------------------------------------
        $display("\n=================================================");
        $display(" Results: %0d passed, %0d failed (%0d total)",
                  pass_count, fail_count, pass_count + fail_count);
        $display("=================================================\n");
 
        $finish;
    end
 
endmodule

sv_dMem/dMem_tb.vcd
$date
	Mon Jul 13 17:47:12 2026
$end
$version
	Icarus Verilog
$end
$timescale
	1ps
$end
$scope module dMem_tb $end
$var wire 32 ! read_data [31:0] $end
$var parameter 32 " CLK_PERIOD $end
$var parameter 32 # DEPTH $end
$var parameter 3 $ F3_B $end
$var parameter 3 % F3_BU $end
$var parameter 3 & F3_H $end
$var parameter 3 ' F3_HU $end
$var parameter 3 ( F3_W $end
$var reg 32 ) addr [31:0] $end
$var reg 1 * clk $end
$var reg 3 + funct3 [2:0] $end
$var reg 1 , mem_write $end
$var reg 32 - rand_addr [31:0] $end
$var reg 32 . rand_data [31:0] $end
$var reg 32 / write_data [31:0] $end
$var integer 32 0 fail_count [31:0] $end
$var integer 32 1 pass_count [31:0] $end
$scope module dut $end
$var wire 32 2 addr [31:0] $end
$var wire 1 * clk $end
$var wire 3 3 funct3 [2:0] $end
$var wire 1 , mem_write $end
$var wire 32 4 raw_word [31:0] $end
$var wire 32 5 write_data [31:0] $end
$var wire 4 6 word_addr [3:0] $end
$var wire 32 7 shifted_rdata [31:0] $end
$var wire 2 8 byte_offset [1:0] $end
$var parameter 32 9 DEPTH $end
$var parameter 32 : WORD_BITS $end
$var reg 4 ; byte_enable [3:0] $end
$var reg 32 < read_data [31:0] $end
$var reg 32 = shifted_wdata [31:0] $end
$scope begin $ivl_for_loop0 $end
$var integer 32 > i [31:0] $end
$upscope $end
$upscope $end
$scope begin $ivl_for_loop1 $end
$var integer 32 ? i [31:0] $end
$upscope $end
$scope task check $end
$upscope $end
$scope task do_load $end
$upscope $end
$scope task do_store $end
$upscope $end
$upscope $end
$enddefinitions $end
$comment Show the parameter values. $end
$dumpall
b100 :
b10000 9
b10 (
b101 '
b1 &
b100 %
b0 $
b10000 #
b1010 "
$end
#0
$dumpvars
b0 ?
b10000 >
b0 =
b0 <
b1 ;
b0 8
b0 7
b0 6
b0 5
b0 4
b0 3
b0 2
b0 1
b0 0
b0 /
bx .
bx -
0,
b0 +
0*
b0 )
b0 !
$end
#5000
1*
#6000
b1111 ;
b11011110101011011011111011101111 =
1,
b10 +
b10 3
b11011110101011011011111011101111 /
b11011110101011011011111011101111 5
#10000
0*
#15000
b11011110101011011011111011101111 !
b11011110101011011011111011101111 <
b11011110101011011011111011101111 7
b11011110101011011011111011101111 4
1*
#16000
0,
#17000
b0 !
b0 <
b10010001101000101011001111000 =
b0 7
b0 4
b1 6
1,
b10010001101000101011001111000 /
b10010001101000101011001111000 5
b100 )
b100 2
b1 1
#20000
0*
#25000
b10010001101000101011001111000 !
b10010001101000101011001111000 <
b10010001101000101011001111000 7
b10010001101000101011001111000 4
1*
#26000
0,
#27000
b0 !
b0 <
b11001010111111101111000000001101 =
b0 7
b0 4
b1111 6
1,
b11001010111111101111000000001101 /
b11001010111111101111000000001101 5
b111100 )
b111100 2
b10 1
#30000
0*
#35000
b11001010111111101111000000001101 !
b11001010111111101111000000001101 <
b11001010111111101111000000001101 7
b11001010111111101111000000001101 4
1*
#36000
0,
#37000
b11011110101011011011111011101111 !
b11011110101011011011111011101111 <
b11011110101011011011111011101111 7
b11011110101011011011111011101111 4
b0 6
b0 )
b0 2
b11 1
#38000
b0 !
b0 <
b0 =
b0 7
b0 4
b10 6
1,
b0 /
b0 5
b1000 )
b1000 2
b100 1
#40000
0*
#45000
1*
#46000
b1 ;
b10101010 =
b0 +
b0 3
b10101010 /
b10101010 5
1,
#50000
0*
#55000
b11111111111111111111111110101010 !
b11111111111111111111111110101010 <
b10101010 7
b10101010 4
1*
#56000
b10101010 !
b10101010 <
b1111 ;
b10 +
b10 3
0,
#57000
b0 !
b0 <
b10 ;
b1011101100000000 =
b0 7
b1 8
1,
b0 +
b0 3
b10111011 /
b10111011 5
b1001 )
b1001 2
b101 1
#60000
0*
#65000
b11111111111111111111111110111011 !
b11111111111111111111111110111011 <
b10111011 7
b1011101110101010 4
1*
#66000
b1011101110101010 !
b1011101110101010 <
b1111 ;
b10111011 =
b1011101110101010 7
b0 8
b10 +
b10 3
b1000 )
b1000 2
0,
#67000
b0 !
b0 <
b100 ;
b110011000000000000000000 =
b0 7
b10 8
1,
b0 +
b0 3
b11001100 /
b11001100 5
b1010 )
b1010 2
b110 1
#70000
0*
#75000
b11111111111111111111111111001100 !
b11111111111111111111111111001100 <
b11001100 7
b110011001011101110101010 4
1*
#76000
b110011001011101110101010 !
b110011001011101110101010 <
b1111 ;
b11001100 =
b110011001011101110101010 7
b0 8
b10 +
b10 3
b1000 )
b1000 2
0,
#77000
b0 !
b0 <
b1000 ;
b11011101000000000000000000000000 =
b0 7
b11 8
1,
b0 +
b0 3
b11011101 /
b11011101 5
b1011 )
b1011 2
b111 1
#80000
0*
#85000
b11111111111111111111111111011101 !
b11111111111111111111111111011101 <
b11011101 7
b11011101110011001011101110101010 4
1*
#86000
b11011101110011001011101110101010 !
b11011101110011001011101110101010 <
b1111 ;
b11011101 =
b11011101110011001011101110101010 7
b0 8
b10 +
b10 3
b1000 )
b1000 2
0,
#87000
b0 !
b0 <
b0 =
b0 7
b0 4
b11 6
1,
b0 /
b0 5
b1100 )
b1100 2
b1000 1
#90000
0*
#95000
1*
#96000
b11 ;
b1001000110100 =
b1 +
b1 3
b1001000110100 /
b1001000110100 5
1,
#100000
0*
#105000
b1001000110100 !
b1001000110100 <
b1001000110100 7
b1001000110100 4
1*
#106000
b1111 ;
b10 +
b10 3
0,
#107000
b0 !
b0 <
b1100 ;
b1010110011110000000000000000000 =
b0 7
b10 8
1,
b1 +
b1 3
b101011001111000 /
b101011001111000 5
b1110 )
b1110 2
b1001 1
#110000
0*
#115000
b101011001111000 !
b101011001111000 <
b101011001111000 7
b1010110011110000001001000110100 4
1*
#116000
b1010110011110000001001000110100 !
b1010110011110000001001000110100 <
b1111 ;
b101011001111000 =
b1010110011110000001001000110100 7
b0 8
b10 +
b10 3
b1100 )
b1100 2
0,
#117000
b11111111111111111111111111101111 !
b11111111111111111111111111101111 <
b1 ;
b1111111 =
b11011110101011011011111011101111 7
b11011110101011011011111011101111 4
b0 6
1,
b0 +
b0 3
b1111111 /
b1111111 5
b0 )
b0 2
b1010 1
#120000
0*
#125000
b1111111 !
b1111111 <
b11011110101011011011111001111111 7
b11011110101011011011111001111111 4
1*
#126000
0,
#127000
b100 +
b100 3
b1011 1
#128000
b10000000 =
1,
b0 +
b0 3
b10000000 /
b10000000 5
b1100 1
#130000
0*
#135000
b11111111111111111111111110000000 !
b11111111111111111111111110000000 <
b11011110101011011011111010000000 7
b11011110101011011011111010000000 4
1*
#136000
0,
#137000
b10000000 !
b10000000 <
b100 +
b100 3
b1101 1
#138000
b11111111111111111011111010000000 !
b11111111111111111011111010000000 <
b11 ;
b111111111111111 =
1,
b1 +
b1 3
b111111111111111 /
b111111111111111 5
b1110 1
#140000
0*
#145000
b111111111111111 !
b111111111111111 <
b11011110101011010111111111111111 7
b11011110101011010111111111111111 4
1*
#146000
0,
#147000
b101 +
b101 3
b1111 1
#148000
b1000000001010101 =
1,
b1 +
b1 3
b1000000001010101 /
b1000000001010101 5
b10000 1
#150000
0*
#155000
b11111111111111111000000001010101 !
b11111111111111111000000001010101 <
b11011110101011011000000001010101 7
b11011110101011011000000001010101 4
1*
#156000
0,
#157000
b1000000001010101 !
b1000000001010101 <
b101 +
b101 3
b10001 1
#158000
b0 !
b0 <
b1111 ;
b10000001000000100000001110000100 =
b0 7
b0 4
b100 6
1,
b10 +
b10 3
b10000001000000100000001110000100 /
b10000001000000100000001110000100 5
b10000 )
b10000 2
b10010 1
#160000
0*
#165000
b10000001000000100000001110000100 !
b10000001000000100000001110000100 <
b10000001000000100000001110000100 7
b10000001000000100000001110000100 4
1*
#166000
b11111111111111111111111110000100 !
b11111111111111111111111110000100 <
b1 ;
b0 +
b0 3
0,
#167000
b11 !
b11 <
b10 ;
b10000000111000010000000000 =
b100000010000001000000011 7
b1 8
b10001 )
b10001 2
b10011 1
#168000
b10 !
b10 <
b100 ;
b11100001000000000000000000 =
b1000000100000010 7
b10 8
b10010 )
b10010 2
b10100 1
#169000
b11111111111111111111111110000001 !
b11111111111111111111111110000001 <
b1000 ;
b10000100000000000000000000000000 =
b10000001 7
b11 8
b10011 )
b10011 2
b10101 1
#170000
b10000100 !
b10000100 <
b1 ;
b10000001000000100000001110000100 =
b10000001000000100000001110000100 7
b0 8
b100 +
b100 3
b10000 )
b10000 2
b10110 1
0*
#171000
b10000001 !
b10000001 <
b1000 ;
b10000100000000000000000000000000 =
b10000001 7
b11 8
b10011 )
b10011 2
b10111 1
#172000
b0 !
b0 <
b1111 ;
b10101010101010101010101010101010 =
b0 4
b110 6
b0 7
b0 8
1,
b10 +
b10 3
b10101010101010101010101010101010 /
b10101010101010101010101010101010 5
b11000 )
b11000 2
b11000 1
#175000
b10101010101010101010101010101010 !
b10101010101010101010101010101010 <
b10101010101010101010101010101010 7
b10101010101010101010101010101010 4
1*
#176000
b1010101010101010101010101010101 =
b1010101010101010101010101010101 /
b1010101010101010101010101010101 5
0,
#180000
0*
#185000
1*
#187000
b0 !
b0 <
b10001000100010001000100010001 =
b0 7
b0 4
b111 6
1,
b10001000100010001000100010001 /
b10001000100010001000100010001 5
b11100 )
b11100 2
b11001 1
#190000
0*
#195000
b10001000100010001000100010001 !
b10001000100010001000100010001 <
b10001000100010001000100010001 7
b10001000100010001000100010001 4
1*
#196000
b100010001000100010001000100010 =
b100010001000100010001000100010 /
b100010001000100010001000100010 5
1,
#200000
0*
#205000
b100010001000100010001000100010 !
b100010001000100010001000100010 <
b100010001000100010001000100010 7
b100010001000100010001000100010 4
1*
#206000
0,
#207000
b0 !
b0 <
b0 =
b0 7
b0 4
b1000 6
1,
b0 /
b0 5
b100000 )
b100000 2
b11010 1
#210000
0*
#215000
1*
#216000
b0 ;
b11111111111111111111111111111111 =
b11 +
b11 3
b11111111111111111111111111111111 /
b11111111111111111111111111111111 5
1,
#220000
0*
#225000
1*
#226000
b1111 ;
b10 +
b10 3
0,
#227000
b1001 6
1,
b100100 )
b100100 2
b11011 1
#230000
0*
#235000
b11111111111111111111111111111111 !
b11111111111111111111111111111111 <
b11111111111111111111111111111111 7
b11111111111111111111111111111111 4
1*
#236000
b0 !
b0 <
b110 +
b110 3
0,
#237000
b0 ;
b111 +
b111 3
b11100 1
#238000
b1111 ;
b0 7
b0 4
b1010 6
b10 +
b10 3
b101000 )
b101000 2
b11101 1
#239000
b11111111111111111111111111111111 !
b11111111111111111111111111111111 <
b1000000100010010101111010000001 =
b11111111111111111111111111111111 7
b11111111111111111111111111111111 4
b1001 6
1,
b1000000100010010101111010000001 /
b1000000100010010101111010000001 5
b100100 )
b100100 2
b1000000100010010101111010000001 .
b100100 -
b11110 1
#240000
0*
#245000
b1000000100010010101111010000001 !
b1000000100010010101111010000001 <
b1000000100010010101111010000001 7
b1000000100010010101111010000001 4
1*
#246000
0,
#247000
b11011110101011011000000001010101 !
b11011110101011011000000001010101 <
b110001111100000101011001100011 =
b11011110101011011000000001010101 7
b11011110101011011000000001010101 4
b0 6
1,
b110001111100000101011001100011 /
b110001111100000101011001100011 5
b0 )
b0 2
b110001111100000101011001100011 .
b0 -
b1 ?
b11111 1
#250000
0*
#255000
b110001111100000101011001100011 !
b110001111100000101011001100011 <
b110001111100000101011001100011 7
b110001111100000101011001100011 4
1*
#256000
0,
#257000
b0 !
b0 <
b11000110110111111001100110001101 =
b0 7
b0 4
b1000 6
1,
b11000110110111111001100110001101 /
b11000110110111111001100110001101 5
b100000 )
b100000 2
b11000110110111111001100110001101 .
b100000 -
b10 ?
b100000 1
#260000
0*
#265000
b11000110110111111001100110001101 !
b11000110110111111001100110001101 <
b11000110110111111001100110001101 7
b11000110110111111001100110001101 4
1*
#266000
0,
#267000
b1010110011110000001001000110100 !
b1010110011110000001001000110100 <
b1001001101110101001000010010 =
b1010110011110000001001000110100 7
b1010110011110000001001000110100 4
b11 6
1,
b1001001101110101001000010010 /
b1001001101110101001000010010 5
b1100 )
b1100 2
b1001001101110101001000010010 .
b1100 -
b11 ?
b100001 1
#270000
0*
#275000
b1001001101110101001000010010 !
b1001001101110101001000010010 <
b1001001101110101001000010010 7
b1001001101110101001000010010 4
1*
#276000
0,
#277000
b11000110110111111001100110001101 !
b11000110110111111001100110001101 <
b10000110110101111100110100001101 =
b11000110110111111001100110001101 7
b11000110110111111001100110001101 4
b1000 6
1,
b10000110110101111100110100001101 /
b10000110110101111100110100001101 5
b100000 )
b100000 2
b10000110110101111100110100001101 .
b100000 -
b100 ?
b100010 1
#280000
0*
#285000
b10000110110101111100110100001101 !
b10000110110101111100110100001101 <
b10000110110101111100110100001101 7
b10000110110101111100110100001101 4
1*
#286000
0,
#287000
b0 !
b0 <
b10011110100011011100110100111101 =
b0 7
b0 4
b1011 6
1,
b10011110100011011100110100111101 /
b10011110100011011100110100111101 5
b101100 )
b101100 2
b10011110100011011100110100111101 .
b101100 -
b101 ?
b100011 1
#290000
0*
#295000
b10011110100011011100110100111101 !
b10011110100011011100110100111101 <
b10011110100011011100110100111101 7
b10011110100011011100110100111101 4
1*
#296000
0,
#297000
b11001010111111101111000000001101 !
b11001010111111101111000000001101 <
b11000110001011011111011110001100 =
b11001010111111101111000000001101 7
b11001010111111101111000000001101 4
b1111 6
1,
b11000110001011011111011110001100 /
b11000110001011011111011110001100 5
b111100 )
b111100 2
b11000110001011011111011110001100 .
b111100 -
b110 ?
b100100 1
#300000
0*
#305000
b11000110001011011111011110001100 !
b11000110001011011111011110001100 <
b11000110001011011111011110001100 7
b11000110001011011111011110001100 4
1*
#306000
0,
#307000
b1100011001101110010010011000110 =
1,
b1100011001101110010010011000110 /
b1100011001101110010010011000110 5
b1100011001101110010010011000110 .
b111 ?
b100101 1
#310000
0*
#315000
b1100011001101110010010011000110 !
b1100011001101110010010011000110 <
b1100011001101110010010011000110 7
b1100011001101110010010011000110 4
1*
#316000
0,
#317000
b10101010101010101010101010101010 !
b10101010101010101010101010101010 <
b1010101000100111101001010101010 =
b10101010101010101010101010101010 7
b10101010101010101010101010101010 4
b110 6
1,
b1010101000100111101001010101010 /
b1010101000100111101001010101010 5
b11000 )
b11000 2
b1010101000100111101001010101010 .
b11000 -
b1000 ?
b100110 1
#320000
0*
#325000
b1010101000100111101001010101010 !
b1010101000100111101001010101010 <
b1010101000100111101001010101010 7
b1010101000100111101001010101010 4
1*
#326000
0,
#327000
b1100011001101110010010011000110 !
b1100011001101110010010011000110 <
b111011110100100111001001110111 =
b1100011001101110010010011000110 7
b1100011001101110010010011000110 4
b1111 6
1,
b111011110100100111001001110111 /
b111011110100100111001001110111 5
b111100 )
b111100 2
b111011110100100111001001110111 .
b111100 -
b1001 ?
b100111 1
#330000
0*
#335000
b111011110100100111001001110111 !
b111011110100100111001001110111 <
b111011110100100111001001110111 7
b111011110100100111001001110111 4
1*
#336000
0,
#337000
b110001111100000101011001100011 !
b110001111100000101011001100011 <
b11000111111011001101101110001111 =
b110001111100000101011001100011 7
b110001111100000101011001100011 4
b0 6
1,
b11000111111011001101101110001111 /
b11000111111011001101101110001111 5
b0 )
b0 2
b11000111111011001101101110001111 .
b0 -
b1010 ?
b101000 1
#340000
0*
#345000
b11000111111011001101101110001111 !
b11000111111011001101101110001111 <
b11000111111011001101101110001111 7
b11000111111011001101101110001111 4
1*
#346000
0,
#347000
b111011110100100111001001110111 !
b111011110100100111001001110111 <
b1100111011101101001011011001110 =
b111011110100100111001001110111 7
b111011110100100111001001110111 4
b1111 6
1,
b1100111011101101001011011001110 /
b1100111011101101001011011001110 5
b111100 )
b111100 2
b1100111011101101001011011001110 .
b111100 -
b1011 ?
b101001 1
#350000
0*
#355000
b1100111011101101001011011001110 !
b1100111011101101001011011001110 <
b1100111011101101001011011001110 7
b1100111011101101001011011001110 4
1*
#356000
0,
#357000
b100010001000100010001000100010 !
b100010001000100010001000100010 <
b1100010110010100100111011000101 =
b100010001000100010001000100010 7
b100010001000100010001000100010 4
b111 6
1,
b1100010110010100100111011000101 /
b1100010110010100100111011000101 5
b11100 )
b11100 2
b1100010110010100100111011000101 .
b11100 -
b1100 ?
b101010 1
#360000
0*
#365000
b1100010110010100100111011000101 !
b1100010110010100100111011000101 <
b1100010110010100100111011000101 7
b1100010110010100100111011000101 4
1*
#366000
0,
#367000
b0 !
b0 <
b1011110100011100010100010111101 =
b0 7
b0 4
b1010 6
1,
b1011110100011100010100010111101 /
b1011110100011100010100010111101 5
b101000 )
b101000 2
b1011110100011100010100010111101 .
b101000 -
b1101 ?
b101011 1
#370000
0*
#375000
b1011110100011100010100010111101 !
b1011110100011100010100010111101 <
b1011110100011100010100010111101 7
b1011110100011100010100010111101 4
1*
#376000
0,
#377000
b10010001101000101011001111000 !
b10010001101000101011001111000 <
b110010101001110010011001100101 =
b10010001101000101011001111000 7
b10010001101000101011001111000 4
b1 6
1,
b110010101001110010011001100101 /
b110010101001110010011001100101 5
b100 )
b100 2
b110010101001110010011001100101 .
b100 -
b1110 ?
b101100 1
#380000
0*
#385000
b110010101001110010011001100101 !
b110010101001110010011001100101 <
b110010101001110010011001100101 7
b110010101001110010011001100101 4
1*
#386000
0,
#387000
b1001001101110101001000010010 !
b1001001101110101001000010010 <
b10000101011100111000011100001010 =
b1001001101110101001000010010 7
b1001001101110101001000010010 4
b11 6
1,
b10000101011100111000011100001010 /
b10000101011100111000011100001010 5
b1100 )
b1100 2
b10000101011100111000011100001010 .
b1100 -
b1111 ?
b101101 1
#390000
0*
#395000
b10000101011100111000011100001010 !
b10000101011100111000011100001010 <
b10000101011100111000011100001010 7
b10000101011100111000011100001010 4
1*
#396000
0,
#397000
b10000001000000100000001110000100 !
b10000001000000100000001110000100 <
b10010000011001000010000100100000 =
b10000001000000100000001110000100 7
b10000001000000100000001110000100 4
b100 6
1,
b10010000011001000010000100100000 /
b10010000011001000010000100100000 5
b10000 )
b10000 2
b10010000011001000010000100100000 .
b10000 -
b10000 ?
b101110 1
#400000
0*
#405000
b10010000011001000010000100100000 !
b10010000011001000010000100100000 <
b10010000011001000010000100100000 7
b10010000011001000010000100100000 4
1*
#406000
0,
#407000
b0 !
b0 <
b1001110110011001100110010011101 =
b0 7
b0 4
b1101 6
1,
b1001110110011001100110010011101 /
b1001110110011001100110010011101 5
b110100 )
b110100 2
b1001110110011001100110010011101 .
b110100 -
b10001 ?
b101111 1
#410000
0*
#415000
b1001110110011001100110010011101 !
b1001110110011001100110010011101 <
b1001110110011001100110010011101 7
b1001110110011001100110010011101 4
1*
#416000
0,
#417000
b10010000011001000010000100100000 !
b10010000011001000010000100100000 <
b1001100000111011100000010011 =
b10010000011001000010000100100000 7
b10010000011001000010000100100000 4
b100 6
1,
b1001100000111011100000010011 /
b1001100000111011100000010011 5
b10000 )
b10000 2
b1001100000111011100000010011 .
b10000 -
b10010 ?
b110000 1
#420000
0*
#425000
b1001100000111011100000010011 !
b1001100000111011100000010011 <
b1001100000111011100000010011 7
b1001100000111011100000010011 4
1*
#426000
0,
#427000
b11000111111011001101101110001111 !
b11000111111011001101101110001111 <
b101001101001111101011001010011 =
b11000111111011001101101110001111 7
b11000111111011001101101110001111 4
b0 6
1,
b101001101001111101011001010011 /
b101001101001111101011001010011 5
b0 )
b0 2
b101001101001111101011001010011 .
b0 -
b10011 ?
b110001 1
#430000
0*
